ide50/__init__.py
ide50/__main__.py
ide50/locale/es/LC_MESSAGES/ide50.mo
ide50/locale/es/LC_MESSAGES/ide50.po
ide50-1.0.5.dist-info/LICENSE
ide50-1.0.5.dist-info/METADATA
ide50-1.0.5.dist-info/WHEEL
ide50-1.0.5.dist-info/entry_points.txt
ide50-1.0.5.dist-info/top_level.txt
ide50-1.0.5.dist-info/RECORD
